odoo/addons/delivery_carrier_agency/README.rst
odoo/addons/delivery_carrier_agency/__init__.py
odoo/addons/delivery_carrier_agency/__manifest__.py
odoo/addons/delivery_carrier_agency/i18n/delivery_carrier_agency.pot
odoo/addons/delivery_carrier_agency/i18n/es.po
odoo/addons/delivery_carrier_agency/i18n/it.po
odoo/addons/delivery_carrier_agency/models/__init__.py
odoo/addons/delivery_carrier_agency/models/delivery_carrier_agency.py
odoo/addons/delivery_carrier_agency/models/stock_picking.py
odoo/addons/delivery_carrier_agency/readme/CONTRIBUTORS.rst
odoo/addons/delivery_carrier_agency/readme/DESCRIPTION.rst
odoo/addons/delivery_carrier_agency/security/ir.model.access.csv
odoo/addons/delivery_carrier_agency/static/description/icon.png
odoo/addons/delivery_carrier_agency/static/description/index.html
odoo/addons/delivery_carrier_agency/tests/__init__.py
odoo/addons/delivery_carrier_agency/tests/test_carrier_agency.py
odoo/addons/delivery_carrier_agency/views/delivery_carrier_agency_view.xml
odoo14_addon_delivery_carrier_agency-14.0.1.0.2.dev10.dist-info/METADATA
odoo14_addon_delivery_carrier_agency-14.0.1.0.2.dev10.dist-info/WHEEL
odoo14_addon_delivery_carrier_agency-14.0.1.0.2.dev10.dist-info/top_level.txt
odoo14_addon_delivery_carrier_agency-14.0.1.0.2.dev10.dist-info/RECORD
